a_selenium2df/LICENSE
a_selenium2df/README.MD
a_selenium2df/__init__.py
a_selenium2df/requirements.txt
a_selenium2df/thirdparty.json
a_selenium2df-0.10.dist-info/LICENSE.rst
a_selenium2df-0.10.dist-info/METADATA
a_selenium2df-0.10.dist-info/WHEEL
a_selenium2df-0.10.dist-info/top_level.txt
a_selenium2df-0.10.dist-info/RECORD
