Metadata-Version: 2.1
Name: a-selenium2df
Version: 0.10
Summary: Get all attributes from each Selenium element in record time
Home-page: https://github.com/hansalemaos/a_selenium2df
Author: Johannes Fischer
Author-email: <aulasparticularesdealemaosp@gmail.com>
License: MIT
Keywords: Selenium,automation
Classifier: Development Status :: 4 - Beta
Classifier: Programming Language :: Python :: 3 :: Only
Classifier: Programming Language :: Python :: 3.9
Classifier: Topic :: Scientific/Engineering :: Visualization
Classifier: Topic :: Software Development :: Libraries :: Python Modules
Classifier: Topic :: Text Editors :: Text Processing
Classifier: Topic :: Text Processing :: General
Classifier: Topic :: Text Processing :: Indexing
Classifier: Topic :: Text Processing :: Filters
Classifier: Topic :: Utilities
License-File: LICENSE.rst
Requires-Dist: a-selenium-iframes-crawler
Requires-Dist: check-if-nan
Requires-Dist: flatten-everything
Requires-Dist: pandas
Requires-Dist: regex
Requires-Dist: useful-functions-easier-life
